libscrc/__init__.py
libscrc/_crc16.cpython-37m-x86_64-linux-gnu.so
libscrc/_crc64.cpython-37m-x86_64-linux-gnu.so
libscrc/_crcx.cpython-37m-x86_64-linux-gnu.so
libscrc/_canx.cpython-37m-x86_64-linux-gnu.so
libscrc/_crc82.py
libscrc/_crc8.cpython-37m-x86_64-linux-gnu.so
libscrc/_crc24.cpython-37m-x86_64-linux-gnu.so
libscrc/_crc32.cpython-37m-x86_64-linux-gnu.so
libscrc/test/canx.py
libscrc/test/crc32.py
libscrc/test/modbus.py
libscrc/test/crcx.py
libscrc/test/crc16.py
libscrc/test/crc24.py
libscrc/test/crc8.py
libscrc/test/crc64.py
libscrc/test/hacker.py
libscrc/plugins/convert.py
libscrc-1.8.1.dist-info/WHEEL
libscrc-1.8.1.dist-info/METADATA
libscrc-1.8.1.dist-info/top_level.txt
libscrc-1.8.1.dist-info/LICENSE
libscrc-1.8.1.dist-info/RECORD
