Metadata-Version: 1.1
Name: libscrc
Version: 1.8.1
Summary: Library for calculating CRC3/CRC4/CRC8/CRC16/CRC24/CRC32/CRC64/CRC82
Home-page: https://github.com/hex-in/libscrc
Author: Heyn
Author-email: heyunhuan@gmail.com
License: UNKNOWN
Keywords: CRC3,CRC4,CRC5,CRC6,CRC7,CRC8,CRC16,CRC24,CRC32,CRC64,CRC82
Platform: any
Classifier: Development Status :: 4 - Beta
Classifier: Intended Audience :: Developers
Classifier: Topic :: Software Development :: Libraries :: Python Modules
Classifier: License :: OSI Approved :: GNU General Public License v3 or later (GPLv3+)
Classifier: Programming Language :: Python :: 2
Classifier: Programming Language :: Python :: 2.7
Classifier: Programming Language :: Python :: 3
Classifier: Programming Language :: Python :: 3.4
Classifier: Programming Language :: Python :: 3.5
Classifier: Programming Language :: Python :: 3.6
Classifier: Programming Language :: Python :: 3.7
Classifier: Programming Language :: Python :: 3.8
Classifier: Programming Language :: Python :: 3.9
Classifier: Programming Language :: Python :: 3.10
Classifier: Programming Language :: Python :: Implementation :: CPython
Classifier: Programming Language :: Python :: Implementation :: PyPy
